twitter.common.java-0.3.11-py2.7-nspkg.pth
twitter/common/java/__init__.py
twitter/common/java/attribute_info.py
twitter/common/java/class_file.py
twitter/common/java/class_flags.py
twitter/common/java/constant.py
twitter/common/java/field_info.py
twitter/common/java/java_types.py
twitter/common/java/method_info.py
twitter/common/java/signature_parser.py
twitter/common/java/util.py
twitter/common/java/perfdata/__init__.py
twitter/common/java/perfdata/attribute_buffer.py
twitter/common/java/perfdata/constants.py
twitter/common/java/perfdata/builders/__init__.py
twitter/common/java/perfdata/builders/perfdata2.py
twitter.common.java-0.3.11.dist-info/DESCRIPTION.rst
twitter.common.java-0.3.11.dist-info/METADATA
twitter.common.java-0.3.11.dist-info/RECORD
twitter.common.java-0.3.11.dist-info/WHEEL
twitter.common.java-0.3.11.dist-info/metadata.json
twitter.common.java-0.3.11.dist-info/namespace_packages.txt
twitter.common.java-0.3.11.dist-info/top_level.txt
twitter.common.java-0.3.11.dist-info/zip-safe
